c3po/CollaborativeDataManager.py
c3po/CollaborativeExchanger.py
c3po/CollaborativeObject.py
c3po/CollaborativePhysicsDriver.py
c3po/Coupler.py
c3po/DataAccessor.py
c3po/DataManager.py
c3po/Exchanger.py
c3po/LocalDataManager.py
c3po/LocalExchanger.py
c3po/PhysicsDriver.py
c3po/TimeAccumulator.py
c3po/VERSION
c3po/__init__.py
c3po/couplers/AdaptiveResidualBalanceCoupler.py
c3po/couplers/AndersonCoupler.py
c3po/couplers/CrossedSecantCoupler.py
c3po/couplers/DynamicResidualBalanceCoupler.py
c3po/couplers/FixedPointCoupler.py
c3po/couplers/JFNKCoupler.py
c3po/couplers/__init__.py
c3po/exchangeMethods/DirectMatching.py
c3po/exchangeMethods/ExchangeMethod.py
c3po/exchangeMethods/SharedRemapping.py
c3po/exchangeMethods/SharedRemappingMulti1D3D.py
c3po/exchangeMethods/__init__.py
c3po/medcouplingCompat/__init__.py
c3po/mpi/MPICollaborativeDataManager.py
c3po/mpi/MPICollaborativePhysicsDriver.py
c3po/mpi/MPICollectiveDataManager.py
c3po/mpi/MPICollectiveProcess.py
c3po/mpi/MPICoupler.py
c3po/mpi/MPIDomainDecompositionDataManager.py
c3po/mpi/MPIExchanger.py
c3po/mpi/MPIMasterDataManager.py
c3po/mpi/MPIMasterExchanger.py
c3po/mpi/MPIMasterPhysicsDriver.py
c3po/mpi/MPIRecipient.py
c3po/mpi/MPIRemote.py
c3po/mpi/MPIRemoteProcess.py
c3po/mpi/MPIRemoteProcesses.py
c3po/mpi/MPISender.py
c3po/mpi/MPITag.py
c3po/mpi/MPIWorker.py
c3po/mpi/__init__.py
c3po/mpi/mpiExchangeMethods/MPIExchangeMethod.py
c3po/mpi/mpiExchangeMethods/MPISharedRemapping.py
c3po/mpi/mpiExchangeMethods/MPISharedRemappingMulti1D3D.py
c3po/mpi/mpiExchangeMethods/MPIValueBcast.py
c3po/mpi/mpiExchangeMethods/__init__.py
c3po/multi1D/Grid.py
c3po/multi1D/MEDInterface.py
c3po/multi1D/Multi1DAPI.py
c3po/multi1D/Multi1DPhysicsDriver.py
c3po/multi1D/__init__.py
c3po/multi1D/mpi/MPIMulti1DPhysicsDriver.py
c3po/multi1D/mpi/__init__.py
c3po/physicsDrivers/ALCYONE2Driver.py
c3po/physicsDrivers/APOLLO3Driver.py
c3po/physicsDrivers/CATHARE2Driver.py
c3po/physicsDrivers/CATHARE3Driver.py
c3po/physicsDrivers/CRONOS2Driver.py
salome_c3po-2.4.1.dist-info/METADATA
salome_c3po-2.4.1.dist-info/WHEEL
salome_c3po-2.4.1.dist-info/top_level.txt
salome_c3po-2.4.1.dist-info/RECORD
